graphitepusher/__init__.py
graphitepusher/graphite.py
graphitepusher-0.5.0.dist-info/LICENSE
graphitepusher-0.5.0.dist-info/METADATA
graphitepusher-0.5.0.dist-info/WHEEL
graphitepusher-0.5.0.dist-info/top_level.txt
graphitepusher-0.5.0.dist-info/RECORD
