Metadata-Version: 2.1
Name: graphitepusher
Version: 0.5.0
Summary: A client library that pushes data to Graphite by pickle format.
Home-page: https://github.com/yanagisawa-kentaro-777/graphitepusher
Author: YANAGISAWA, Kentaro
Author-email: yanagisawa.kentaro@weidenthal.co.jp
License: GNU General Public License v3 (GPLv3)
Keywords: graphite
Platform: UNKNOWN
Classifier: Development Status :: 4 - Beta
Classifier: License :: OSI Approved :: GNU General Public License v3 (GPLv3)
Classifier: Programming Language :: Python
Classifier: Programming Language :: Python :: 3.6
Classifier: Topic :: Office/Business :: Financial
Classifier: Topic :: Software Development :: Libraries :: Python Modules
Requires-Dist: python-dateutil (>=2.8.0)
